WordReplaceEngine/PDF_Model.py
WordReplaceEngine/Word_Model.py
WordReplaceEngine/__init__.py
wordreplaceengine-1.0.1.dist-info/licenses/LICENSE.txt
wordreplaceengine-1.0.1.dist-info/METADATA
wordreplaceengine-1.0.1.dist-info/WHEEL
wordreplaceengine-1.0.1.dist-info/top_level.txt
wordreplaceengine-1.0.1.dist-info/RECORD
