Metadata-Version: 2.4
Name: WordReplaceEngine
Version: 1.0.1
Summary: A Python engine for automated word replacement in Word documents
Author-email: Yun-De Huang <startime_electronics@orztrickster.com>
License: AGPL-3.0-only
Project-URL: Homepage, https://github.com/orztrickster/WordReplaceEngine
Classifier: Topic :: Software Development :: Libraries
Classifier: Topic :: Office/Business
Requires-Python: >=3.11
License-File: LICENSE.txt
Requires-Dist: python-docx
Requires-Dist: Pillow
Requires-Dist: pywin32; platform_system == "Windows"
Dynamic: license-file
